[
        {
            "quote": "Success is a journey, not a race."
        },
        {
            "quote": "Believe in yourself and push on."
        },
        {
            "quote": "You are stronger than you think."
        },
        {
            "quote": "Every day is a chance to improve."
        },
        {
            "quote": "Do it with passion or not at all."
        },
        {
            "quote": "Progress, not perfection."
        },
        {
            "quote": "Dream it. Plan it. Do it."
        },
        {
            "quote": "Good things take time. Be patient."
        },
        {
            "quote": "Never stop learning and growing."
        },
        {
            "quote": "Small actions lead to big changes."
        },
        {
            "quote": "Start now, not tomorrow."
        },
        {
            "quote": "Success is built on daily effort."
        },
        {
            "quote": "Don’t wait for opportunity. Create it."
        },
        {
            "quote": "Focus on progress, not perfection."
        },
        {
            "quote": "Consistency is key to achievement."
        },
        {
            "quote": "Push forward. You've got this."
        },
        {
            "quote": "Keep going, no matter how tough."
        },
        {
            "quote": "Action is the foundation of success."
        },
        {
            "quote": "Don't quit. Do it for your future."
        },
        {
            "quote": "Success starts with a single step."
        },
        {
            "quote": "Stay positive, work hard, succeed."
        },
        {
            "quote": "The best time to start is now."
        },
        {
            "quote": "Your future is created by your now."
        },
        {
            "quote": "Opportunities don’t happen, create them."
        },
        {
            "quote": "The journey is the reward."
        },
        {
            "quote": "Don’t fear failure; fear not trying."
        },
        {
            "quote": "Create the life you can’t wait for."
        },
        {
            "quote": "Make each day your masterpiece."
        },
        {
            "quote": "Doubt kills more dreams than failure."
        },
        {
            "quote": "Stay humble. Stay hungry."
        }
    ]